test_client_176883/__init__.py
test_client_176883/add_item.py
test_client_176883/client.py
test_client_176883/test.py
test_client_176883/api_request/__init__.py
test_client_176883/api_request/add_item.py
test_client_176883-1.0.3.dist-info/METADATA
test_client_176883-1.0.3.dist-info/WHEEL
test_client_176883-1.0.3.dist-info/top_level.txt
test_client_176883-1.0.3.dist-info/RECORD
