Metadata-Version: 2.1
Name: test-client-176883
Version: 1.0.3
Summary: TYPE YOUR DESCRIPTION HERE
Home-page: https://github.com/thuan1412
Author: Thuan do
Author-email: thuan14121999@gmail.com
License: MIT
Keywords: SOME,MEANINGFULL,KEYWORDS
Platform: UNKNOWN
Classifier: Development Status :: 3 - Alpha
Classifier: Intended Audience :: Developers
Classifier: Topic :: Software Development :: Build Tools
Classifier: License :: OSI Approved :: MIT License
Classifier: Programming Language :: Python :: 3
Classifier: Programming Language :: Python :: 3.4
Classifier: Programming Language :: Python :: 3.5
Classifier: Programming Language :: Python :: 3.6
Requires-Dist: requests
